mcp_arduino_server/__init__.py
mcp_arduino_server/config.py
mcp_arduino_server/server_refactored.py
mcp_arduino_server/components/__init__.py
mcp_arduino_server/components/arduino_board.py
mcp_arduino_server/components/arduino_boards_advanced.py
mcp_arduino_server/components/arduino_compile_advanced.py
mcp_arduino_server/components/arduino_debug.py
mcp_arduino_server/components/arduino_libraries_advanced.py
mcp_arduino_server/components/arduino_library.py
mcp_arduino_server/components/arduino_serial.py
mcp_arduino_server/components/arduino_sketch.py
mcp_arduino_server/components/arduino_system_advanced.py
mcp_arduino_server/components/circular_buffer.py
mcp_arduino_server/components/client_capabilities.py
mcp_arduino_server/components/client_debug.py
mcp_arduino_server/components/port_checker.py
mcp_arduino_server/components/serial_manager.py
mcp_arduino_server/components/serial_monitor.py
mcp_arduino_server/components/wireviz.py
mcp_arduino_server/components/wireviz_prompts.py
mcp_arduino-2025.9.27.4.dist-info/METADATA
mcp_arduino-2025.9.27.4.dist-info/WHEEL
mcp_arduino-2025.9.27.4.dist-info/entry_points.txt
mcp_arduino-2025.9.27.4.dist-info/licenses/LICENSE
mcp_arduino-2025.9.27.4.dist-info/RECORD
