Metadata-Version: 2.4
Name: mcp-arduino
Version: 2025.9.27.4
Summary: FastMCP-powered Arduino CLI server with WireViz integration for circuit diagrams
Project-URL: Homepage, https://git.supported.systems/MCP/mcp-arduino
Project-URL: Repository, https://git.supported.systems/MCP/mcp-arduino
Project-URL: Issues, https://git.supported.systems/MCP/mcp-arduino/issues
Author-email: Ryan Malloy <ryan@supported.systems>
License-File: LICENSE
Keywords: ai,arduino,arduino-cli,fastmcp,llm,mcp,model context protocol,wireviz
Classifier: Development Status :: 4 - Beta
Classifier: Intended Audience :: Developers
Classifier: License :: OSI Approved :: MIT License
Classifier: Operating System :: OS Independent
Classifier: Programming Language :: Python :: 3
Classifier: Programming Language :: Python :: 3.10
Classifier: Programming Language :: Python :: 3.11
Classifier: Programming Language :: Python :: 3.12
Classifier: Topic :: Scientific/Engineering :: Artificial Intelligence
Classifier: Topic :: Software Development :: Embedded Systems
Requires-Python: >=3.10
Requires-Dist: fastmcp>=2.12.4
Requires-Dist: pyserial-asyncio>=0.6
Requires-Dist: pyserial>=3.5
Requires-Dist: thefuzz[speedup]>=0.22.1
Requires-Dist: wireviz>=0.4.1
Provides-Extra: dev
Requires-Dist: mypy>=1.5.0; extra == 'dev'
Requires-Dist: pytest-asyncio>=0.21.0; extra == 'dev'
Requires-Dist: pytest-cov>=7.0.0; extra == 'dev'
Requires-Dist: pytest>=8.4.2; extra == 'dev'
Requires-Dist: ruff>=0.13.2; extra == 'dev'
Requires-Dist: watchdog>=3.0.0; extra == 'dev'
